aib/__init__.py
aib/bridge.py
aib/cli.py
aib/config.py
aib/models.py
aib/batch/__init__.py
aib/batch/base.py
aib/batch/gemini.py
aib/batch/qwen.py
aib/vendors/__init__.py
aib/vendors/base.py
aib/vendors/gemini.py
aib/vendors/kimi.py
aib/vendors/openai.py
aib/vendors/qwen.py
ai_abridge-1.0.0.dist-info/METADATA
ai_abridge-1.0.0.dist-info/WHEEL
ai_abridge-1.0.0.dist-info/entry_points.txt
ai_abridge-1.0.0.dist-info/RECORD
