Metadata-Version: 2.4
Name: ai-Abridge
Version: 1.0.0
Summary: A pure AI model bridge - transparent, native SDK, multi-vendor support.
License-Expression: MIT
Keywords: ai,batch,gemini,kimi,llm,openai,qwen
Classifier: Development Status :: 4 - Beta
Classifier: Intended Audience :: Developers
Classifier: License :: OSI Approved :: MIT License
Classifier: Programming Language :: Python :: 3
Classifier: Programming Language :: Python :: 3.9
Classifier: Programming Language :: Python :: 3.10
Classifier: Programming Language :: Python :: 3.11
Classifier: Programming Language :: Python :: 3.12
Requires-Python: >=3.9
Requires-Dist: dashscope>=1.0.0
Requires-Dist: google-genai>=1.0.0
Requires-Dist: openai>=1.0.0
Requires-Dist: pyyaml>=6.0
Requires-Dist: typer>=0.9.0
